autopack/__init__.py
autopack/cli.py
autopack/evaluation.py
autopack/exporters.py
autopack/prune.py
autopack/publish.py
autopack/quantize.py
autopack/scan.py
autopack/state.py
autopack_grn-0.1.5.0.dist-info/METADATA
autopack_grn-0.1.5.0.dist-info/WHEEL
autopack_grn-0.1.5.0.dist-info/entry_points.txt
autopack_grn-0.1.5.0.dist-info/licenses/LICENSE
autopack_grn-0.1.5.0.dist-info/RECORD
