Metadata-Version: 2.4
Name: autopack-grn
Version: 0.1.5.0
Summary: CLI to quantize and release Hugging Face models in multiple formats
Author: GranulaVision
License: Apache-2.0
License-File: LICENSE
Keywords: bitsandbytes,gguf,huggingface,onnx,quantization,transformers
Classifier: License :: OSI Approved :: Apache Software License
Classifier: Operating System :: OS Independent
Classifier: Programming Language :: Python :: 3
Requires-Python: >=3.9
Requires-Dist: accelerate>=0.30.0
Requires-Dist: bitsandbytes>=0.43.0; platform_system != 'Windows'
Requires-Dist: datasets
Requires-Dist: huggingface-hub>=0.24.0
Requires-Dist: safetensors>=0.4.2
Requires-Dist: torch>=2.1.0
Requires-Dist: tqdm>=4.66.0
Requires-Dist: transformers>=4.41.0
Provides-Extra: gguf
Requires-Dist: numpy>=1.26.0; extra == 'gguf'
Provides-Extra: llama
Requires-Dist: llama-cpp-python>=0.2.84; (platform_system != 'Windows') and extra == 'llama'
Provides-Extra: onnx
Requires-Dist: onnxruntime>=1.18.0; extra == 'onnx'
Requires-Dist: optimum[onnxruntime]>=1.17.0; extra == 'onnx'
